wkflws_slack/__init__.py
wkflws_slack/send_message.py
wkflws_slack/triggers/__init__.py
wkflws_slack/triggers/receive_message.py
wkflws_slack-0.1.2.dist-info/LICENSE
wkflws_slack-0.1.2.dist-info/METADATA
wkflws_slack-0.1.2.dist-info/WHEEL
wkflws_slack-0.1.2.dist-info/top_level.txt
wkflws_slack-0.1.2.dist-info/RECORD
